PyNAS/LICENSE
PyNAS/__init__.py
PyNAS/__main__.py
PyNAS/conf.json
PyNAS/config.py
PyNAS/help.json
PyNAS/main.py
PyNAS/main_gui.py
PyNAS/__pycache__/__init__.cpython-39.pyc
PyNAS/__pycache__/__main__.cpython-39.pyc
PyNAS/__pycache__/config.cpython-39.pyc
PyNAS/__pycache__/main.cpython-39.pyc
PyNAS/__pycache__/main_gui.cpython-39.pyc
PyNAS/static/__init__.py
PyNAS/static/login.css
PyNAS/static/css/bootstrap.min.css
PyNAS/static/css/font.scss
PyNAS/static/css/style.min.css
PyNAS/static/css/style.scss
PyNAS/static/fonts/poppins/poppins-v5-latin-300.eot
PyNAS/static/fonts/poppins/poppins-v5-latin-300.svg
PyNAS/static/fonts/poppins/poppins-v5-latin-300.ttf
PyNAS/static/fonts/poppins/poppins-v5-latin-300.woff
PyNAS/static/fonts/poppins/poppins-v5-latin-300.woff2
PyNAS/static/fonts/poppins/poppins-v5-latin-600.eot
PyNAS/static/fonts/poppins/poppins-v5-latin-600.svg
PyNAS/static/fonts/poppins/poppins-v5-latin-600.ttf
PyNAS/static/fonts/poppins/poppins-v5-latin-600.woff
PyNAS/static/fonts/poppins/poppins-v5-latin-600.woff2
PyNAS/static/images/background.jpg
PyNAS/static/images/favicon.ico
PyNAS/static/images/icon.jpg
PyNAS/static/js/jquery-3.4.1.min.js
PyNAS/static/js/main.js
PyNAS/static/vendor/datatable/datatables.min.css
PyNAS/static/vendor/datatable/datatables.min.js
PyNAS/static/vendor/datatable/file-size.js
PyNAS/static/vendor/datatable/DataTables-1.10.18/images/sort_asc.png
PyNAS/static/vendor/datatable/DataTables-1.10.18/images/sort_asc_disabled.png
PyNAS/static/vendor/datatable/DataTables-1.10.18/images/sort_both.png
PyNAS/static/vendor/datatable/DataTables-1.10.18/images/sort_desc.png
PyNAS/static/vendor/datatable/DataTables-1.10.18/images/sort_desc_disabled.png
PyNAS/static/vendor/fontawesome-5.1/css/all.min.css
PyNAS/static/vendor/fontawesome-5.1/webfonts/fa-brands-400.eot
PyNAS/static/vendor/fontawesome-5.1/webfonts/fa-brands-400.svg
PyNAS/static/vendor/fontawesome-5.1/webfonts/fa-brands-400.ttf
PyNAS/static/vendor/fontawesome-5.1/webfonts/fa-brands-400.woff
PyNAS-2022.4.15.dist-info/LICENSE
PyNAS-2022.4.15.dist-info/METADATA
PyNAS-2022.4.15.dist-info/WHEEL
PyNAS-2022.4.15.dist-info/entry_points.txt
PyNAS-2022.4.15.dist-info/top_level.txt
PyNAS-2022.4.15.dist-info/RECORD
