Metadata-Version: 2.1
Name: PyNAS
Version: 2022.4.15
Summary: Python NAS, Based On Updog.
Home-page: http://wufan.fun/
Author: Fan Wu
Author-email: issues@wufan.fun
License: UNKNOWN
Project-URL: Source Code, https://github.com/WindowsRegedit/PyNAS
Keywords: NAS Netdisk Flask Login ConfFile GUI CLI
Platform: UNKNOWN
Classifier: Development Status :: 5 - Production/Stable
Classifier: Intended Audience :: Customer Service
Classifier: License :: OSI Approved :: MIT License
Classifier: Framework :: Flask
Classifier: Topic :: Internet :: File Transfer Protocol (FTP)
Classifier: Programming Language :: Python :: 3.5
Classifier: Programming Language :: Python :: 3.6
Classifier: Programming Language :: Python :: 3.7
Classifier: Programming Language :: Python :: 3.8
Classifier: Programming Language :: Python :: 3.9
License-File: LICENSE
Requires-Dist: colorama (==0.4.4)
Requires-Dist: Flask (==2.1.1)
Requires-Dist: Flask-Login (==0.6.0)
Requires-Dist: Flask-WTF (==1.0.1)
Requires-Dist: pyftpdlib (==1.5.6)
Requires-Dist: requests (==2.25.1)
Requires-Dist: ttkbootstrap (==1.7.4)
Requires-Dist: Werkzeug (==2.0.3)
Requires-Dist: WTForms (==3.0.1)
Requires-Dist: pyOpenSSL (==22.0.0)
